{"edges":[{"endNode":0,"startNode":3},{"endNode":0,"startNode":2},{"endNode":0,"startNode":1},{"endNode":1,"startNode":2},{"endNode":1,"startNode":3},{"endNode":2,"startNode":3}],"labels":[{"color":{"a":1,"b":0,"g":1,"r":0},"labelId":0,"name":"Max"},{"color":{"a":1,"b":0,"g":0,"r":1},"labelId":1,"name":"Person"},{"color":{"a":1,"b":1,"g":0,"r":0},"labelId":2,"name":"Post"}],"name":"Max","nodes":[{"labelId":0,"nodeId":0,"position":{"x":-0.448440671,"y":0.9728969,"z":0.2912809}},{"labelId":0,"nodeId":1,"position":{"x":0.00743572228,"y":1.48820186,"z":0.4483573}},{"labelId":0,"nodeId":2,"position":{"x":-0.665526032,"y":1.59364724,"z":0.491609037}},{"labelId":0,"nodeId":3,"position":{"x":-0.362378925,"y":1.126225,"z":0.9518495}},{"labelId":1,"nodeId":4,"position":{"x":-1.03443956,"y":6.73936,"z":-3.08837724}}],"scale":0.702494144}